{"82c6642a6d34ff9839b339e6062b8faa":{"song":{"time":"23:50","artist":"Justice","name":"genesis","album":"CROSS"},"video":{"kind":"youtube#searchResult","etag":"\"m2yskBQFythfE4irbTIeOgYYfBU/tbIrWVH--V1ckUEazOJgNhjIGeI\"","id":{"kind":"youtube#video","videoId":"VKzWLUQizz8"},"snippet":{"publishedAt":"2012-12-07T17:20:08.000Z","channelId":"UCQ5Ssrs48yJBfOesfDqXUeA","title":"Justice - Genesis - †","description":"New Single \"Randy\" available here : http://smarturl.it/JusticeRandy?IQid=youtube Taken from Justice's new album \"Woman\" Download \"Safe and Sound\" here ...","thumbnails":{"default":{"url":"https://i.ytimg.com/vi/VKzWLUQizz8/default.jpg","width":120,"height":90},"medium":{"url":"https://i.ytimg.com/vi/VKzWLUQizz8/mqdefault.jpg","width":320,"height":180},"high":{"url":"https://i.ytimg.com/vi/VKzWLUQizz8/hqdefault.jpg","width":480,"height":360}},"channelTitle":"Justice","liveBroadcastContent":"none"}}}}